{"forum_title": "RÖFL", "id": "122657", "title": "Sniðugur gæji !", "url": "http://www.live2cruize.com/spjall/showthread.php/122657-Sniðugur-gæji-!", "posts": [{"user_name": "g0tlife", "text": "Þessi gæji er helvíti sniðugur. Vona að þetta sé ekki repost", "date": "2010-05-26 23:31:00", "post_id": 1}, {"user_name": "ManicHead", "text": "Alls ekki slæmt, frekar svalt að nenna að gera þetta allt einn síns liðs. \nSpurning samt hversu mikinn frítíma þessi maður hefur?", "date": "2010-05-27 00:04:00", "post_id": 2}, {"user_name": "intenz", "text": "7 * 3,56 = 24,92 mínútur ... og það er bara ein taka. Svo á eftir að telja video/audio editing og sampling vinnuna.", "date": "2010-05-27 00:37:00", "post_id": 3}, {"user_name": "sindrib", "text": "skelfing eru þeir líkir,, þessir mexicanar eru allir eins <<<icon_smile.gif>>>", "date": "2010-05-27 00:56:00", "post_id": 4}, {"user_name": "Grieg!", "text": "Það er ekkert verið að spara það að troða inná sig.. nóg til í neðravídjóinu! nema þetta sé æxli eða eitthver óþverri..", "date": "2010-05-27 02:13:00", "post_id": 5}, {"user_name": "Loud1", "text": "hahahahahah já vá !", "date": "2010-05-27 02:16:00", "post_id": 6}, {"user_name": "SheDevil", "text": "Ég er ekki að sjá það sama og þú, það sem ég sé eru gallabuxur sem eru hífðar upp á beltinu, og skilja eftir það svæði sem talan er á. \nÞannig að það togast upp sitthvorumegin við .. og lætur þetta líta illa út, en það er engin meiri bunga á þessum buxum en hinum .. skv því sem ég sé eftir að horfa á þetta.", "date": "2010-05-27 02:22:00", "post_id": 7}, {"user_name": "Grieg!", "text": "Ætli ég sé ekki bara svona sár yfir því að vera ekki með svona bungu", "date": "2010-05-27 02:23:00", "post_id": 8}, {"user_name": "Kitty Svarfdal", "text": "frekat töff hjá honum", "date": "2010-05-27 08:04:00", "post_id": 9}, {"user_name": "Viktorkarl", "text": "Þetta er reyndar skelfilega reiknað hjá þér Gaui <<<icon_biggrin.gif>>>\n\nMyndbandið er 3 mín og 56 sek, og ef við segjum okkur að þetta séu sléttar 4 mín þá er það 7 * 4 = 28 mín, en það vantar 4 sekundur af fyrir hvern, þannig þetta eru 28 sek sem detta af samtals, semsagt 28 mín - 28 sek = 27 mínútur og 32 sekúndur <<<icon_biggrin.gif>>>\n\n7 * 3,56 þýðir í rauninni 7 * 3 mín og 31 sek", "date": "2010-05-27 11:20:00", "post_id": 10}, {"user_name": "vladrulli", "text": "haha... þvílík Disney rödd... <<<icon_lol.gif>>>\n\nkann að syngja...", "date": "2010-05-27 21:54:00", "post_id": 11}, {"user_name": "RAT", "text": "Sam Tsui singing, Kurt producing... hann er ekkert einn ... og já Disney rödd dauðans alls ekki ónýt, en ekkert spes <<<icon_smile.gif>>>", "date": "2010-05-27 22:21:00", "post_id": 12}, {"user_name": "RAT", "text": "þeir eiga víst fullt af svona videoum...", "date": "2010-05-27 22:25:00", "post_id": 13}, {"user_name": "BIGBRO", "text": "tjahh menn hafa nú verið að hala inn MIKINN pening á þessari rödd :P en þetta er virkilega töff hjá honum", "date": "2010-05-27 22:47:00", "post_id": 14}, {"user_name": "RAT", "text": "Enda er það á þessari rödd ... hún er ekkert spes lengur :P  Ekki léleg enda væri soldil heimska að segja það ... bara ekkert spes.", "date": "2010-05-27 23:02:00", "post_id": 15}], "file_urls": ["http://live2cruize.com/spjall/images/smilies/icon_smile.gif", "http://live2cruize.com/spjall/images/smilies/icon_biggrin.gif", "http://live2cruize.com/spjall/images/smilies/icon_biggrin.gif", "http://live2cruize.com/spjall/images/smilies/icon_lol.gif", "http://live2cruize.com/spjall/images/smilies/icon_smile.gif"], "date": "2010-05-26 23:31:00", "files": [{"url": "http://live2cruize.com/spjall/images/smilies/icon_smile.gif", "path": "full/1b4c582c326e1f58ed353744337401937e95b553.gif", "checksum": "9ee646ffab71107d1a11407be52f33a5"}, {"url": "http://live2cruize.com/spjall/images/smilies/icon_biggrin.gif", "path": "full/24620e8136e134c2ee38603a088528683844d88a.gif", "checksum": "f970a6591668c625e4b9dbd3b7a450d7"}, {"url": "http://live2cruize.com/spjall/images/smilies/icon_biggrin.gif", "path": "full/24620e8136e134c2ee38603a088528683844d88a.gif", "checksum": "f970a6591668c625e4b9dbd3b7a450d7"}, {"url": "http://live2cruize.com/spjall/images/smilies/icon_lol.gif", "path": "full/fa705ed47e899453195f9b57838cc55ca8fdd97f.gif", "checksum": "b76e7729d43c4a49182d020741285bef"}, {"url": "http://live2cruize.com/spjall/images/smilies/icon_smile.gif", "path": "full/1b4c582c326e1f58ed353744337401937e95b553.gif", "checksum": "9ee646ffab71107d1a11407be52f33a5"}]}