{"forum_title": "RÖFL", "id": "140074", "title": "tengja ps3", "url": "http://www.live2cruize.com/spjall/showthread.php/140074-tengja-ps3", "posts": [{"user_name": "Mr. Skúli", "text": "get ég ekki tengt ps3 við sjónvarp með scart tengi?", "date": "2011-02-10 23:44:00", "post_id": 1}, {"user_name": "veigar thor", "text": "Varstu seinast með hdmi snúru ? Ef svo er, þá þarftu að halda ,,on'' takkanum inni þangað til að seinna ,,bíbið'' heyrist. Þarf allavega að gera það í ps3 Slim hjá mér.", "date": "2011-02-10 23:53:00", "post_id": 2}, {"user_name": "Mr. Skúli", "text": "takk gamli, reddaðir mér þarna ! <<<icon_biggrin.gif>>> var alveg að missa það!", "date": "2011-02-10 23:59:00", "post_id": 3}, {"user_name": "EG6", "text": "strakurinn kominn með ps3 ?", "date": "2011-02-11 11:12:00", "post_id": 4}, {"user_name": "MXW!", "text": "váa..þessi þráður var waste of my time!", "date": "2011-02-11 11:14:00", "post_id": 5}, {"user_name": "-Hjalti-", "text": "Ert þú svona merkilegur pappír ?", "date": "2011-02-11 11:15:00", "post_id": 6}, {"user_name": "MXW!", "text": "er kominn tími á leiðindi?(:\n\nhehe neinei..ekkert frekar, þráðurinn var eiginlega búinn þegar ég átti von á pælingum og samræðum. varð bara svolítið svekktur og ákvað að deila þeirri athugasemd!", "date": "2011-02-11 14:04:00", "post_id": 7}, {"user_name": "Sindri A", "text": "Umræður um að tengja ps3 geta varla verið spennandi", "date": "2011-02-11 14:07:00", "post_id": 8}, {"user_name": "MXW!", "text": "annað hélt ég..þar sem mér datt í hug að það gæti ekki verið flókið að tengja ps3 tölvu. ég hafði rangt fyrir mér..", "date": "2011-02-11 14:17:00", "post_id": 9}, {"user_name": "Bomsi", "text": "Hann tengdi hana alveg rétt, vissi bara ekki að það þyrfti að \"endurræsa\" tölvuna til að hún virki í SD sjónvarpi", "date": "2011-02-11 14:30:00", "post_id": 10}, {"user_name": "MXW!", "text": "það var einmitt það sem ég misskildi og komst að því að þetta var bara tímasóun! hehe", "date": "2011-02-11 15:16:00", "post_id": 11}, {"user_name": "Gunni91", "text": "samt ertu að halda áfram að eyða tíma í nákvæmlega ekki neitt? <<<icon_biggrin.gif>>> Sumir eru alveg........", "date": "2011-02-11 18:34:00", "post_id": 12}, {"user_name": "Skúlimx", "text": "Vá hvað ég lennti í þessu með mína og skildi ekki afhverju í fjandanum hún virkaði ekki og úrskurðaði hana bilaða. Svo googlaði ég þetta vandamál og lausnin fannst :P", "date": "2011-02-13 22:04:00", "post_id": 13}, {"user_name": "Mr. Skúli", "text": "", "date": "2011-02-13 23:35:00", "post_id": 14}, {"user_name": "MXW!", "text": "hahaha<<<icon_biggrin.gif>>>", "date": "2011-02-14 00:18:00", "post_id": 15}], "file_urls": ["http://live2cruize.com/spjall/images/smilies/icon_biggrin.gif", "http://live2cruize.com/spjall/images/smilies/icon_biggrin.gif", "http://live2cruize.com/spjall/images/smilies/icon_biggrin.gif"], "date": "2011-02-10 23:44:00", "files": [{"url": "http://live2cruize.com/spjall/images/smilies/icon_biggrin.gif", "path": "full/24620e8136e134c2ee38603a088528683844d88a.gif", "checksum": "f970a6591668c625e4b9dbd3b7a450d7"}, {"url": "http://live2cruize.com/spjall/images/smilies/icon_biggrin.gif", "path": "full/24620e8136e134c2ee38603a088528683844d88a.gif", "checksum": "f970a6591668c625e4b9dbd3b7a450d7"}, {"url": "http://live2cruize.com/spjall/images/smilies/icon_biggrin.gif", "path": "full/24620e8136e134c2ee38603a088528683844d88a.gif", "checksum": "f970a6591668c625e4b9dbd3b7a450d7"}]}