{"forum_title": "Gallerí", "id": "163436", "title": "b16a buggy edit í 15.pósti", "url": "http://www.live2cruize.com/spjall/showthread.php/163436-b16a-buggy-edit-í-15-pósti", "posts": [{"user_name": "hafsteinn kaffi", "text": "ákvað að skella inn þræði af buggy sem er buinn að vera í huganum lengi , undirbúningur buinn að vera mikill en stundin er runnin upp að smíðinni <<<icon_smile.gif>>>\n\n\n\r\nbyrjaði á því að fá mótorinn og hann kom úr 98 ek civic B16A\n\n\n\r\nKeypti mér síðan suðu Migatronig automig 221 varð fyrir valinu\n\n\n\r\nOg svo var byrjað að stilla upp \"lowerframe\" (botninn)\n\n\n\n\n\r\nallt lowerframe-ið púntktað og tilbúið til suðu.\n\n\n\r\nSuðan.\n\n\n\r\nlowerframe tilbuið \n\r\nSmá edit en hér er teikningin\n\n\n\n\r\nupdate kemur á næstunni <<<icon_smile.gif>>> takk fyrir mig", "date": "2012-04-21 01:28:00", "post_id": 1}, {"user_name": "Aronpals", "text": "Kláraðu þetta fyrst þú ert byrjaður á þessu! alltaf langað í svona tæki.. Lýtur vel út hjá þér", "date": "2012-04-21 07:02:00", "post_id": 2}, {"user_name": "burger", "text": "nettör", "date": "2012-04-21 11:27:00", "post_id": 3}, {"user_name": "Jónan", "text": "Verður gaman að sjá þetta tilbúið", "date": "2012-04-21 11:56:00", "post_id": 4}, {"user_name": "palmisæ", "text": "Þetta er algjör snild <<<icon_biggrin.gif>>> það verður gaman að prufa þetta <<<icon_biggrin.gif>>>", "date": "2012-04-21 13:44:00", "post_id": 5}, {"user_name": "megnuz", "text": "geðveikt\nvar einmitt að skoða þetta albúm um daginn http://www.facebook.com/media/set/?s...4694758&type=1\nværi snilld að eiga svona græju", "date": "2012-04-21 14:17:00", "post_id": 6}, {"user_name": "sakaxxx", "text": "cool verkefni og rosa flott suðan hjá þér<<<icon_thumright.gif>>>", "date": "2012-04-21 15:17:00", "post_id": 7}, {"user_name": "Arnar Ingi", "text": "Gedveikt project !!", "date": "2012-04-23 06:33:00", "post_id": 8}, {"user_name": "Einar Vti", "text": "Thetta er snilld", "date": "2012-04-23 08:28:00", "post_id": 9}, {"user_name": "KKA", "text": "töff project, væri til í að gera svona!", "date": "2012-04-23 09:17:00", "post_id": 10}, {"user_name": "hafsteinn kaffi", "text": "það var eitt sem ég var að pæla í ,, teikningin gerir ráð fyrir vw bjöllu stýrismaskínu ef e-h á svoleiðis endilega að láta mig vita , sparar mér hellings vinnu <<<icon_smile.gif>>>", "date": "2012-04-25 20:39:00", "post_id": 11}, {"user_name": "addistra", "text": "ja sæll hvað þetta er töff", "date": "2012-04-25 21:14:00", "post_id": 12}, {"user_name": "burger", "text": "https://bland.is/messageboard/messag...advid=28086841\nprufa að spurja þennan .\n\nannars sa eg bjöllur til sölu a bland fyrir stuttu og held meira að segja að þær hafi verið i kef en ekki viss . \n\nveit að það var ein bla herna a hringbrautinni", "date": "2012-04-25 23:17:00", "post_id": 13}, {"user_name": "blackhole", "text": "sá einhver rngtoy á facebook linknum?<<<icon_razz.gif>>>", "date": "2012-04-28 17:34:00", "post_id": 14}, {"user_name": "hafsteinn kaffi", "text": "héldum smá áfram í dag, tókum fram og aðalveltiboga og stilltum öllu hárréttu upp, nú fer allt á fullt!", "date": "2012-05-09 23:16:00", "post_id": 15}, {"user_name": "burger", "text": "haffi kaffi ! \n\ntöff stöff svo þurfum við að græja sma smiða vinnu i golf <<<icon_smile.gif>>>", "date": "2012-05-09 23:21:00", "post_id": 16}, {"user_name": "Öddi..", "text": "Myndi bara óska eftir stýrismaskínu á fornbíla spjallinu, þar er hafsjór af mönnum sem vita um allt svona tiltækt.\r\nEf þú færð engar upplýsingar þar af viti þá er sverrir á ystafelli (samgöngu safn) alger snillingur og veit pottþétt um þetta.\n\r\nFlott verkefni og flottar suður !", "date": "2012-05-09 23:42:00", "post_id": 17}, {"user_name": "Mr. Andersen", "text": "Það er slatti að bjöllu dóti til á esjumel Símar 566 7838 og 660 1763.", "date": "2012-05-09 23:55:00", "post_id": 18}, {"user_name": "hafsteinn kaffi", "text": "þakka ykkur fyrir strakar ég verð að skoða þetta <<<icon_smile.gif>>>", "date": "2012-05-10 11:42:00", "post_id": 19}], "file_urls": ["http://live2cruize.com/spjall/images/smilies/icon_smile.gif", "http://live2cruize.com/spjall/images/smilies/icon_smile.gif", "http://live2cruize.com/spjall/images/smilies/icon_biggrin.gif", "http://live2cruize.com/spjall/images/smilies/icon_biggrin.gif", "http://live2cruize.com/spjall/images/smilies/icon_thumright.gif", "http://live2cruize.com/spjall/images/smilies/icon_smile.gif", "http://live2cruize.com/spjall/images/smilies/icon_razz.gif", "http://live2cruize.com/spjall/images/smilies/icon_smile.gif", "http://live2cruize.com/spjall/images/smilies/icon_smile.gif"], "date": "2012-04-21 01:28:00", "files": [{"url": "http://live2cruize.com/spjall/images/smilies/icon_smile.gif", "path": "full/1b4c582c326e1f58ed353744337401937e95b553.gif", "checksum": "9ee646ffab71107d1a11407be52f33a5"}, {"url": "http://live2cruize.com/spjall/images/smilies/icon_smile.gif", "path": "full/1b4c582c326e1f58ed353744337401937e95b553.gif", "checksum": "9ee646ffab71107d1a11407be52f33a5"}, {"url": "http://live2cruize.com/spjall/images/smilies/icon_biggrin.gif", "path": "full/24620e8136e134c2ee38603a088528683844d88a.gif", "checksum": "f970a6591668c625e4b9dbd3b7a450d7"}, {"url": "http://live2cruize.com/spjall/images/smilies/icon_biggrin.gif", "path": "full/24620e8136e134c2ee38603a088528683844d88a.gif", "checksum": "f970a6591668c625e4b9dbd3b7a450d7"}, {"url": "http://live2cruize.com/spjall/images/smilies/icon_thumright.gif", "path": "full/02c06d07c61aabd346099c6953775aea8b70523f.gif", "checksum": "6d67056a8fd1d9908dd01fb776e5aeac"}, {"url": "http://live2cruize.com/spjall/images/smilies/icon_smile.gif", "path": "full/1b4c582c326e1f58ed353744337401937e95b553.gif", "checksum": "9ee646ffab71107d1a11407be52f33a5"}, {"url": "http://live2cruize.com/spjall/images/smilies/icon_razz.gif", "path": "full/3cbd531acc490f313767995ecb2ee199d3f4fe0c.gif", "checksum": "7aec68426aa06f01e2b1ac250e5aee62"}, {"url": "http://live2cruize.com/spjall/images/smilies/icon_smile.gif", "path": "full/1b4c582c326e1f58ed353744337401937e95b553.gif", "checksum": "9ee646ffab71107d1a11407be52f33a5"}, {"url": "http://live2cruize.com/spjall/images/smilies/icon_smile.gif", "path": "full/1b4c582c326e1f58ed353744337401937e95b553.gif", "checksum": "9ee646ffab71107d1a11407be52f33a5"}]}