{
    "forum_title": "Jeppar",
    "id": "11395",
    "title": ".",
    "url": "http://www.jeppaspjall.is/viewtopic.php?f=29&t=11395",
    "posts": [
        {
            "user_name": "dors",
            "text": ".",
            "date": "2012-06-16 22:20:00",
            "post_id": "59252",
            "reply_to_id": false
        },
        {
            "user_name": "TF3HTH",
            "text": "http://ebay.com.au\n og leitaðu að \"patrol gq hinges\"\n-haffi",
            "date": "2012-06-17 00:15:00",
            "post_id": "59260",
            "reply_to_id": "59252"
        }
    ],
    "date": "2012-06-16 22:20:00"
}