{"url": "https://bland.is/umraeda/flytja-til-usa/22346199/?page=5437", "date": "2010-12-07 23:31:20", "id": "22346199", "items": [{"text": "Það kemur til greina hjá mér að flytja til USA fljótlega eftir áramót.\nÞá kemur Washington til greina eða Iowa.\nHafiði einhverja reynslu af þvi að vera þarna?\nHvernig er að komast í nám þar?", "title": "Flytja til USA", "username": "RMR33", "message_id": "22346199", "user_id": "156664", "response_to": null, "datetime": "2010-12-07 23:31:20", "datestring": "7. des. '10, kl: 23:31:20"}, {"response_to": "22346199", "username": "RMR33", "message_id": "22346757", "user_id": "156664", "datetime": "2010-12-08 00:14:19", "datestring": "8. des. '10, kl: 00:14:19", "text": "veit enginn"}, {"response_to": "22346757", "username": "Anídras", "message_id": "22346803", "user_id": "56309", "datetime": "2010-12-08 00:17:56", "datestring": "8. des. '10, kl: 00:17:56", "text": "nei, við erum allar heimskar með sand í píkunni"}, {"response_to": "22346803", "username": "RMR33", "message_id": "22346822", "user_id": "156664", "datetime": "2010-12-08 00:18:57", "datestring": "8. des. '10, kl: 00:18:57", "text": "Einhvernvegin lít ég alltaf niður á fólk sem talar svona."}, {"response_to": "22346803", "username": "abbalabbalú", "message_id": "22346850", "user_id": "59806", "datetime": "2010-12-08 00:20:40", "datestring": "8. des. '10, kl: 00:20:40", "text": "Var fjör á ströndinni?"}]}