{"url": "https://bland.is/umraeda/a-einhver-svona-sima-/29577897/?page=2201", "date": "2012-12-07 12:43:25", "id": "29577897", "items": [{"text": "Nokia asha 300 eða nokia asha 302 ?? Erað pæla  að fá mér svona síma, má velja mér síma í gjöf. En vil ekki eitthvað rándýra og ofurflókna síma :$ hefur einhver reynslu af þessum týpum, eru þeir góðir?!", "title": "Á einhver svona síma?", "username": "daddaskvis", "message_id": "29577897", "user_id": "224841", "response_to": null, "datetime": "2012-12-07 12:43:25", "datestring": "7. des. '12, kl: 12:43:25"}, {"response_to": "29577897", "username": "Lauraa", "message_id": "29577932", "user_id": "179099", "datetime": "2012-12-07 12:58:50", "datestring": "7. des. '12, kl: 12:58:50", "text": "Já hann er alveg fínn og virkar vel og svona, en myndavélin er mjög léleg. Ef að þú ert ekki mikið að taka myndir á símann þá myndi ég bara fá mér hann  ;)"}, {"response_to": "29577897", "username": "froskur.", "message_id": "29578104", "user_id": "174550", "datetime": "2012-12-07 13:54:51", "datestring": "7. des. '12, kl: 13:54:51", "text": "ég á svona og hann er æði ! :)"}]}