{"url": "https://bland.is/umraeda/tr/30385788/?page=1341", "date": "2013-11-30 18:50:06", "id": "30385788", "items": [{"text": "Hvenær borgar TR út? Því mig minnti að það væri alltaf eftir miðnætti s.s 1. sama hvaða dagur það sé,er það rétt eða rangt hjá mér? :)", "title": "TR", "username": "darknight", "message_id": "30385788", "user_id": "76231", "response_to": null, "datetime": "2013-11-30 18:50:06", "datestring": "30. nóv. '13, kl: 18:50:06"}, {"response_to": "30385788", "username": "Tipzy", "message_id": "30385800", "user_id": "26838", "datetime": "2013-11-30 18:53:42", "datestring": "30. nóv. '13, kl: 18:53:42", "text": "Rétt"}, {"response_to": "30385800", "username": "darknight", "message_id": "30385824", "user_id": "76231", "datetime": "2013-11-30 19:07:52", "datestring": "30. nóv. '13, kl: 19:07:52", "text": "ok, þá er það miðnætti á morgun? S.s ekki miðnættið 1.(sem er á milli sunndags og mánudag) heldur á morgun? :)"}, {"response_to": "30385824", "username": "Máni", "message_id": "30385828", "user_id": "154", "datetime": "2013-11-30 19:08:51", "datestring": "30. nóv. '13, kl: 19:08:51", "text": "já eftir næstkomndi miðnætti"}, {"response_to": "30385824", "username": "Kalishi", "message_id": "30385834", "user_id": "261182", "datetime": "2013-11-30 19:10:47", "datestring": "30. nóv. '13, kl: 19:10:47", "text": "Færð borgað í nótt."}, {"response_to": "30385834", "username": "darknight", "message_id": "30385969", "user_id": "76231", "datetime": "2013-11-30 20:22:18", "datestring": "30. nóv. '13, kl: 20:22:18", "text": "já djók misreiknaði mig haha, takk :)"}, {"response_to": "30385788", "username": "gailo", "message_id": "30385973", "user_id": "186201", "datetime": "2013-11-30 20:24:08", "datestring": "30. nóv. '13, kl: 20:24:08", "text": "Bara einsog venjulega."}, {"response_to": "30385973", "username": "darknight", "message_id": "30385986", "user_id": "76231", "datetime": "2013-11-30 20:31:47", "datestring": "30. nóv. '13, kl: 20:31:47", "text": "Æji sá bara í heimabankanum að það kom alltaf inn næsta virka dag ef 1þ er um helgi.. En svo er það greinilega bara yfirlitið :)"}, {"response_to": "30385788", "username": "casablanca", "message_id": "30386765", "user_id": "60300", "datetime": "2013-12-01 02:52:56", "datestring": "1. des. '13, kl: 02:52:56", "text": "Loksins þoli ekki þetta peningaleysi"}, {"response_to": "30385788", "username": "casablanca", "message_id": "30386766", "user_id": "60300", "datetime": "2013-12-01 02:53:24", "datestring": "1. des. '13, kl: 02:53:24", "text": "Jibbi faum utborgað"}]}