{"url": "https://bland.is/umraeda/hvad-ertu-ad-gera-i-kvold-/30881256/?page=796", "date": "2014-10-18 21:40:58", "id": "30881256", "items": [{"text": "?", "title": "Hvað ertu að gera í kvöld?", "username": "Twitters", "message_id": "30881256", "user_id": "100064", "response_to": null, "datetime": "2014-10-18 21:40:58", "datestring": "18. okt. '14, kl: 21:40:58"}, {"response_to": "30881256", "username": "Mae West", "message_id": "30881261", "user_id": "28460", "datetime": "2014-10-18 21:44:03", "datestring": "18. okt. '14, kl: 21:44:03", "text": "Ég er að reyna halda mér vakandi. Lukkaðist ekki í gær, þá sofnaði ég úr leiðindum snemma."}, {"response_to": "30881261", "username": "Twitters", "message_id": "30881264", "user_id": "100064", "datetime": "2014-10-18 21:44:28", "datestring": "18. okt. '14, kl: 21:44:28", "text": "næs :)"}, {"response_to": "30881261", "username": "Anteros", "message_id": "30881266", "user_id": "31384", "datetime": "2014-10-18 21:44:40", "datestring": "18. okt. '14, kl: 21:44:40", "text": "Ekkert slæmt við það að sofna snemma."}, {"response_to": "30881256", "username": "hafrun123", "message_id": "30881269", "user_id": "283152", "datetime": "2014-10-18 21:46:21", "datestring": "18. okt. '14, kl: 21:46:21", "text": "var að fara á deit, búin að henda mér í sturtu og klæða mig og mála mig... neinei, deitið hringir og segir að hann sé svo þreyttur að við ættum bara að hittast á morgun, hann ætli snemma að sofa..."}, {"response_to": "30881269", "username": "Twitters", "message_id": "30881272", "user_id": "100064", "datetime": "2014-10-18 21:46:50", "datestring": "18. okt. '14, kl: 21:46:50", "text": "æi en fúllt"}, {"response_to": "30881272", "username": "hafrun123", "message_id": "30881277", "user_id": "283152", "datetime": "2014-10-18 21:49:33", "datestring": "18. okt. '14, kl: 21:49:33", "text": "já ég sem var búin að hlakka mega mikið til!"}, {"response_to": "30881269", "username": "Anteros", "message_id": "30881280", "user_id": "31384", "datetime": "2014-10-18 21:50:47", "datestring": "18. okt. '14, kl: 21:50:47", "text": "Þvílíkur dóni."}, {"response_to": "30881280", "username": "hafrun123", "message_id": "30881283", "user_id": "283152", "datetime": "2014-10-18 21:51:42", "datestring": "18. okt. '14, kl: 21:51:42", "text": "æj nei, hann er yndislegur og það var ástæða fyrir því að hann var þreyttur svo ég var ekkert að bögga hann með því (s.s hann svaf ekki í nótt)"}, {"response_to": "30881283", "username": "Anteros", "message_id": "30881286", "user_id": "31384", "datetime": "2014-10-18 21:52:07", "datestring": "18. okt. '14, kl: 21:52:07", "text": "hmmm"}, {"response_to": "30881286", "username": "hafrun123", "message_id": "30881292", "user_id": "283152", "datetime": "2014-10-18 21:53:12", "datestring": "18. okt. '14, kl: 21:53:12", "text": "kannski kemur þetta vitlaust út, en ég s.s var meira pirruð yfir því að ÉG væri að missa af skemmtilegu kvöldi heldur en hann hefði beilað... ef ég hugsa bara um sjálfa mig en ekki hann;)"}, {"response_to": "30881292", "username": "Anteros", "message_id": "30881294", "user_id": "31384", "datetime": "2014-10-18 21:54:01", "datestring": "18. okt. '14, kl: 21:54:01", "text": "Því skyldir þú ekki hugsa um sjálfa þig."}, {"response_to": "30881294", "username": "hafrun123", "message_id": "30881312", "user_id": "283152", "datetime": "2014-10-18 21:57:35", "datestring": "18. okt. '14, kl: 21:57:35", "text": "hahah já auðvitað á maður að gera það, en ég ætla ekki að eyða kvöldinu í pirring! Hlakka bara til að sjá hann á morgun í staðinn (og ég hef fullt af hlutum sem ég get þá nýtt kvöldið í að klára)"}, {"response_to": "30881280", "username": "Mae West", "message_id": "30881304", "user_id": "28460", "datetime": "2014-10-18 21:55:29", "datestring": "18. okt. '14, kl: 21:55:29", "text": "Heiðarlegur dóni,... Sem er meira en hægt er að segja um marga."}, {"response_to": "30881269", "username": "Mae West", "message_id": "30881298", "user_id": "28460", "datetime": "2014-10-18 21:54:43", "datestring": "18. okt. '14, kl: 21:54:43", "text": "Vonandi tekuru því ekki persónulega. Ég hef stundum látið svona við fólk bara af því ég er illa upplögð."}, {"response_to": "30881298", "username": "hafrun123", "message_id": "30881308", "user_id": "283152", "datetime": "2014-10-18 21:56:40", "datestring": "18. okt. '14, kl: 21:56:40", "text": "já neinei, tek þessu alls ekkert persónulega :) Vissi að hann væri þreyttur (svaf ekkert síðustu nótt), svo ég bjóst alveg við því að hann myndi frekar vilja fara snemma að sofa til að vera hress á morgun. Hann stakk samt upp á hitting á morgun að fyrra bragði svo það var smá sárabót hehe :)"}, {"response_to": "30881256", "username": "Maluettan", "message_id": "30881270", "user_id": "3056", "datetime": "2014-10-18 21:46:49", "datestring": "18. okt. '14, kl: 21:46:49", "text": "Þarf að læra smá,er að horfa á mynd, borða ostapopp og nammi og spá í að fá mér ískalt malt&appelsin. En þú?"}, {"response_to": "30881270", "username": "Twitters", "message_id": "30881279", "user_id": "100064", "datetime": "2014-10-18 21:50:31", "datestring": "18. okt. '14, kl: 21:50:31", "text": "ég er bara eitthvað að hanga á netinu og er að reyna að finna mér eitthvað til að glápa á"}, {"response_to": "30881256", "username": "Catalyst", "message_id": "30881271", "user_id": "81856", "datetime": "2014-10-18 21:46:49", "datestring": "18. okt. '14, kl: 21:46:49", "text": "Eins og er stend eg við stigann og bíð eftir að afkvæmin sofni i herbergjum sínum. Svo er planið að læra og borða nammi hehehe"}, {"response_to": "30881256", "username": "labbalingur", "message_id": "30881287", "user_id": "48325", "datetime": "2014-10-18 21:52:12", "datestring": "18. okt. '14, kl: 21:52:12", "text": "Er bara að slaka á eftir erfiðan dag. Það var verið að jarða pabba minn í dag og maður er alveg eins og loftlaus blaðra og hálf dofinn."}, {"response_to": "30881287", "username": "Twitters", "message_id": "30881319", "user_id": "100064", "datetime": "2014-10-18 22:00:54", "datestring": "18. okt. '14, kl: 22:00:54", "text": "samhryggist"}, {"response_to": "30881319", "username": "labbalingur", "message_id": "30881328", "user_id": "48325", "datetime": "2014-10-18 22:04:44", "datestring": "18. okt. '14, kl: 22:04:44", "text": "Takk."}, {"response_to": "30881287", "username": "Mae West", "message_id": "30881346", "user_id": "28460", "datetime": "2014-10-18 22:15:36", "datestring": "18. okt. '14, kl: 22:15:36", "text": "Samhryggist þér líka. Leiðinlegt að lesa svona."}, {"response_to": "30881287", "username": "Anímóna", "message_id": "30881448", "user_id": "86179", "datetime": "2014-10-18 23:19:27", "datestring": "18. okt. '14, kl: 23:19:27", "text": "Samúðarkveðjur og knús"}, {"response_to": "30881287", "username": "She is", "message_id": "30881451", "user_id": "45783", "datetime": "2014-10-18 23:20:09", "datestring": "18. okt. '14, kl: 23:20:09", "text": "innilegar samúðarkveðjur"}, {"response_to": "30881256", "username": "Tipzy", "message_id": "30881310", "user_id": "26838", "datetime": "2014-10-18 21:57:22", "datestring": "18. okt. '14, kl: 21:57:22", "text": "Horfa á Haven og surfa á netinu."}, {"response_to": "30881256", "username": "GoGoYubari", "message_id": "30881315", "user_id": "69201", "datetime": "2014-10-18 21:59:50", "datestring": "18. okt. '14, kl: 21:59:50", "text": "Er að drepast úr greddu að horfa á Sherlock aka Benedikt Cumberbatch..."}, {"response_to": "30881315", "username": "Twitters", "message_id": "30881340", "user_id": "100064", "datetime": "2014-10-18 22:12:02", "datestring": "18. okt. '14, kl: 22:12:02", "text": "úúúú næs"}, {"response_to": "30881340", "username": "GoGoYubari", "message_id": "30881342", "user_id": "69201", "datetime": "2014-10-18 22:13:11", "datestring": "18. okt. '14, kl: 22:13:11", "text": "Enjoy"}, {"response_to": "30881256", "username": "DarKhaireDwomAn", "message_id": "30881316", "user_id": "162498", "datetime": "2014-10-18 22:00:11", "datestring": "18. okt. '14, kl: 22:00:11", "text": "hanga á netinu horfa á tv og éta pizzu"}, {"response_to": "30881256", "username": "QI", "message_id": "30881423", "user_id": "223573", "datetime": "2014-10-18 23:01:50", "datestring": "18. okt. '14, kl: 23:01:50", "text": "Akúrat núna að hlægja að Grjónu,,, :) mínustakkinn er hennar ær og kýr.. :)"}, {"response_to": "30881256", "username": "Anímóna", "message_id": "30881454", "user_id": "86179", "datetime": "2014-10-18 23:20:30", "datestring": "18. okt. '14, kl: 23:20:30", "text": "Gefa brjóst"}, {"response_to": "30881256", "username": "Zagara", "message_id": "30881463", "user_id": "68119", "datetime": "2014-10-18 23:29:16", "datestring": "18. okt. '14, kl: 23:29:16", "text": "Heimabíókvöld! Sæng og prjónar og læti, bráðum þarf ég svo að grafa kertin upp úr geymslu."}, {"response_to": "30881463", "username": "Twitters", "message_id": "30881464", "user_id": "100064", "datetime": "2014-10-18 23:29:38", "datestring": "18. okt. '14, kl: 23:29:38", "text": "næs"}, {"response_to": "30881256", "username": "Þjóðarblómið", "message_id": "30881469", "user_id": "48048", "datetime": "2014-10-18 23:36:43", "datestring": "18. okt. '14, kl: 23:36:43", "text": "Ég er nýkomin heim úr borgarferð, skrapp í Kringluna og IKEA í dag og eyddi fullt af pening! Það sem ég keypti er svo þungt að það bíður í bílnum þangað til hjálparsveitin kemur á morgun að bera það upp og setja það saman."}, {"response_to": "30881256", "username": "júbb", "message_id": "30881470", "user_id": "40135", "datetime": "2014-10-18 23:36:56", "datestring": "18. okt. '14, kl: 23:36:56", "text": "Horfa á The Originals og borða snickers. Voða lítið annað, er hálfhandlama eftir daginn."}, {"response_to": "30881470", "username": "Twitters", "message_id": "30881476", "user_id": "100064", "datetime": "2014-10-18 23:41:52", "datestring": "18. okt. '14, kl: 23:41:52", "text": "hvað varstu að gera í dag?"}, {"response_to": "30881476", "username": "júbb", "message_id": "30881507", "user_id": "40135", "datetime": "2014-10-19 00:00:06", "datestring": "19. okt. '14, kl: 00:00:06", "text": "Það er það versta, gerði ekkert spes en var með svo mikla vöðvakippi að höndin á mér var eins og hún væri ofvirk. Hefði kannski átt að blanda slatta af kokteilum til að hristingurinn hefði eitthvað gagn. Ég er vön skjálfta og kippum en ég aldrei séð annað eins og ég fæ núna. Það er varla hægt að kalla þetta kippi."}, {"response_to": "30881507", "username": "Twitters", "message_id": "30881511", "user_id": "100064", "datetime": "2014-10-19 00:00:47", "datestring": "19. okt. '14, kl: 00:00:47", "text": "farðu til læknis kona"}, {"response_to": "30881511", "username": "júbb", "message_id": "30881514", "user_id": "40135", "datetime": "2014-10-19 00:02:47", "datestring": "19. okt. '14, kl: 00:02:47", "text": "Þetta er væntanlega þrýstingurinn á taugina út í handlegg, er að vinna á því að minnka hann. En mér er eiginlega hætt að vera sama þannig að ég hringi pottþétt í gigtarlækninn á mánudag."}, {"response_to": "30881256", "username": "Lakkrisbiti", "message_id": "30881496", "user_id": "137532", "datetime": "2014-10-18 23:53:35", "datestring": "18. okt. '14, kl: 23:53:35", "text": "Var að koma heim úr keilu, núna er bara að glápa á bíómynd og borða kannski smá snakk með"}, {"response_to": "30881496", "username": "Twitters", "message_id": "30881515", "user_id": "100064", "datetime": "2014-10-19 00:03:03", "datestring": "19. okt. '14, kl: 00:03:03", "text": "hvaða mynd ertu að horfa á?"}, {"response_to": "30881515", "username": "Lakkrisbiti", "message_id": "30881537", "user_id": "137532", "datetime": "2014-10-19 00:12:14", "datestring": "19. okt. '14, kl: 00:12:14", "text": "moms night out, sá hana á vodafone leigunni"}, {"response_to": "30881537", "username": "lost in iceland", "message_id": "30881604", "user_id": "161862", "datetime": "2014-10-19 01:15:17", "datestring": "19. okt. '14, kl: 01:15:17", "text": "Mátt endilega segja mér hvernig hún er , var að pæla í að horfa á hana en get ekki ákveðið mig hvort þetta sé skemmtileg þvæla eða bara þvæla."}, {"response_to": "30881604", "username": "Lakkrisbiti", "message_id": "30881605", "user_id": "137532", "datetime": "2014-10-19 01:18:09", "datestring": "19. okt. '14, kl: 01:18:09", "text": "Hún er alveg ágæt, fín skemmtileg þvæla bara :)"}, {"response_to": "30881256", "username": "JungleDrum", "message_id": "30881513", "user_id": "29871", "datetime": "2014-10-19 00:02:31", "datestring": "19. okt. '14, kl: 00:02:31", "text": "Ég er bara að slaka á, opnaði eina hvíta eftir að börnin sofnuðu, eiginmaðurinn er á ferðalagi og ég er að njóta þess að vera ein í þögninni :)"}, {"response_to": "30881256", "username": "strákamamma", "message_id": "30881519", "user_id": "11836", "datetime": "2014-10-19 00:05:40", "datestring": "19. okt. '14, kl: 00:05:40", "text": "horfa á greys....með rauðvín að skála við sjálfa mig yfir því að hafa gift mig í dag...  húsbandið er sofnað"}, {"response_to": "30881519", "username": "Twitters", "message_id": "30881521", "user_id": "100064", "datetime": "2014-10-19 00:06:17", "datestring": "19. okt. '14, kl: 00:06:17", "text": "vá í alvöru?   til hamingju"}, {"response_to": "30881521", "username": "strákamamma", "message_id": "30881525", "user_id": "11836", "datetime": "2014-10-19 00:06:52", "datestring": "19. okt. '14, kl: 00:06:52", "text": "takk :)"}, {"response_to": "30881519", "username": "Heiðlóan ♫♬♪ ♩", "message_id": "30881528", "user_id": "267951", "datetime": "2014-10-19 00:08:41", "datestring": "19. okt. '14, kl: 00:08:41", "text": "Til hamingju! Var það víkingagifting?"}, {"response_to": "30881528", "username": "strákamamma", "message_id": "30881530", "user_id": "11836", "datetime": "2014-10-19 00:09:51", "datestring": "19. okt. '14, kl: 00:09:51", "text": "haha.."}, {"response_to": "30881530", "username": "Heiðlóan ♫♬♪ ♩", "message_id": "30881534", "user_id": "267951", "datetime": "2014-10-19 00:10:45", "datestring": "19. okt. '14, kl: 00:10:45", "text": "Aha... þú færð svona prufutíma í viku til að reyna á þetta :)"}, {"response_to": "30881534", "username": "strákamamma", "message_id": "30881538", "user_id": "11836", "datetime": "2014-10-19 00:12:16", "datestring": "19. okt. '14, kl: 00:12:16", "text": "það er það sem ég er að reyna að segja sjálfri mér....   það að hann sé sofnaður og að ég sé ein vakandi ætti auðvitað að láta mig skjálfa í stigvélunum mínum   :P"}, {"response_to": "30881534", "username": "strákamamma", "message_id": "30881539", "user_id": "11836", "datetime": "2014-10-19 00:12:28", "datestring": "19. okt. '14, kl: 00:12:28", "text": "en hey,......   hvernig þekkjust við :P"}, {"response_to": "30881539", "username": "Heiðlóan ♫♬♪ ♩", "message_id": "30881545", "user_id": "267951", "datetime": "2014-10-19 00:22:44", "datestring": "19. okt. '14, kl: 00:22:44", "text": "Ég og þú? Bara á blandinu held ég... ég mundi bara að þú varst að tala um væntanlegt víkingabrúðkaup hér um daginn"}, {"response_to": "30881545", "username": "strákamamma", "message_id": "30881548", "user_id": "11836", "datetime": "2014-10-19 00:25:52", "datestring": "19. okt. '14, kl: 00:25:52", "text": "ah....ok :P"}, {"response_to": "30881256", "username": "247259", "message_id": "30881540", "user_id": "81605", "datetime": "2014-10-19 00:15:13", "datestring": "19. okt. '14, kl: 00:15:13", "text": "Fór í mat til vinkonu minnar áðan, kom svo heim og setti saman og skreytti köku fyrir barnaafmæli á morgun. Nú ligg ég uppí rúmi að bíða eftir að bakið hætti að reyna að myrða mig með verkjum."}, {"response_to": "30881256", "username": "skjáta", "message_id": "30881585", "user_id": "4982", "datetime": "2014-10-19 01:07:31", "datestring": "19. okt. '14, kl: 01:07:31", "text": "Ég var að vinna og er bara nýlega komin heim og er bara að slaka á og ná mér niður eftir vaktina, er alltaf smá tíma að ná mér niður eftir kvöldvaktir."}, {"response_to": "30881256", "username": "Ragga81", "message_id": "30881586", "user_id": "33320", "datetime": "2014-10-19 01:08:40", "datestring": "19. okt. '14, kl: 01:08:40", "text": "Lítið sem ekkert.  Skrapp í smá heimsókn áðan.  Er svo bara að einbeita mér að því að gera sem minst."}, {"response_to": "30881256", "username": "Hvusslags", "message_id": "30881591", "user_id": "241944", "datetime": "2014-10-19 01:10:57", "datestring": "19. okt. '14, kl: 01:10:57", "text": "Horfa á Ace Ventura :)"}, {"response_to": "30881591", "username": "Twitters", "message_id": "30881595", "user_id": "100064", "datetime": "2014-10-19 01:12:07", "datestring": "19. okt. '14, kl: 01:12:07", "text": "næs"}, {"response_to": "30881595", "username": "Hvusslags", "message_id": "30881634", "user_id": "241944", "datetime": "2014-10-19 01:46:35", "datestring": "19. okt. '14, kl: 01:46:35", "text": "jább, búin að horfa á báðar myndirnar :)"}]}