{"url": "https://bland.is/umraeda/lekamalid/30919792/?page=750", "date": "2014-11-18 18:21:26", "id": "30919792", "items": [{"text": "Er einhver með stuttu útgáfuna yfir það sem hefur komið fram í fjölmiðlum síðustu daga?", "title": "Lekamálið", "username": "Helgust", "message_id": "30919792", "user_id": "147413", "response_to": null, "datetime": "2014-11-18 18:21:26", "datestring": "18. nóv. '14, kl: 18:21:26"}, {"response_to": "30919792", "username": "Andý", "message_id": "30919798", "user_id": "62139", "datetime": "2014-11-18 18:28:31", "datestring": "18. nóv. '14, kl: 18:28:31", "text": "Já ég"}]}