{
    "forum_title": "Leikjasalurinn",
    "id": "23154",
    "title": "BF2 íslenskir spilarar !!",
    "url": "https://spjall.vaktin.is/viewtopic.php?f=14&t=23154",
    "posts": [
        {
            "user_name": "ÓmarSmith",
            "text": "Hverjir hérna eru ennþá að spila BF2  eða langar að byrja að spila hann aftur.\nÉg var að byrja að spila hann aftur eftir 2 ára hlé og dauðlangar að finna íslenskan server eða slatta af íslenskum spilurum sem eru tilbúnir að byrja aftur.\nEndilega látið ljós ykkar skína á þessum þræði og látið þetta berast. Spurning hvort e-rjir hérna hafi verið í TEK og OBY sem voru nokkuð magnaður hópur.\nLets do this !!\nKv. Ericsson - BF2  2009",
            "date": "2009-05-14 14:30:00",
            "post_id": "206965",
            "reply_to_id": false
        },
        {
            "user_name": "Pisc3s",
            "text": "Mögnuð timing... var að setja leikinn upp fyrir svona 5 mínútum! \nLangaði að prufa þennan leik aftur, hef samt nánast ekkert spilað hann og hef ekkert vit á honum.",
            "date": "2009-05-14 14:35:00",
            "post_id": "206967",
            "reply_to_id": "206965"
        },
        {
            "user_name": "CendenZ",
            "text": "ég spila hann reglulega.\npingar flott á bresku serverunum.\njá, sárvantar íslenska menningu, verst er að það þurfa alveg að vera 200 active spilarar til að þetta virki.",
            "date": "2009-05-14 16:00:00",
            "post_id": "206973",
            "reply_to_id": "206967"
        },
        {
            "user_name": "Zimbi",
            "text": "ef það kemur íslenskur server þá byrja ég að spila hann aftur.",
            "date": "2009-05-14 17:56:00",
            "post_id": "206980",
            "reply_to_id": "206973"
        },
        {
            "user_name": "KrissiK",
            "text": "sama hérna (Y)",
            "date": "2009-05-14 18:05:00",
            "post_id": "206981",
            "reply_to_id": "206980"
        },
        {
            "user_name": "vesley",
            "text": "seldi minn síðasta sumar : (   og langar aftur í hann : (",
            "date": "2009-05-14 18:38:00",
            "post_id": "206985",
            "reply_to_id": "206981"
        },
        {
            "user_name": "Sydney",
            "text": "Spila eiginlega bara Project Reality núna, normal BF2 er soddan drasl núorðið.",
            "date": "2009-05-14 19:45:00",
            "post_id": "206993",
            "reply_to_id": "206985"
        },
        {
            "user_name": "ÓmarSmith",
            "text": "Það má e-r tala við Tölvutek strákana og fá þá aftur inn.\nSíðan þeirra er ennþá uppi en engin hreyfing virðist hafa verið í næstum ár sýnist mér.\nÉg var alveg farinn að sakna Bf2 og veður gaman að spila aftur. Það geetur ekki annað verið en það séu amk 100 virkir BF2 spilarar á þessu 300.000 manna skeri,.",
            "date": "2009-05-14 23:04:00",
            "post_id": "207019",
            "reply_to_id": "206993"
        },
        {
            "user_name": "Kobbmeister",
            "text": "Ég týndi disknum mínum á lani \n og ég er ekki að finna gott crack því leikurinn er alltaf að slökkva á sér (hef bara prófað einhver 3 \"cröck\") svo ef að einhver veit um gott crack þá má endilega gefa upp download link",
            "date": "2009-05-14 23:17:00",
            "post_id": "207023",
            "reply_to_id": "207019"
        },
        {
            "user_name": "Sydney",
            "text": "Mini-image maður.",
            "date": "2009-05-14 23:23:00",
            "post_id": "207025",
            "reply_to_id": "207023"
        },
        {
            "user_name": "ÓmarSmith",
            "text": "reddaðu þér bara cd key\npottþétt e-r sem á hann og notar ekki.",
            "date": "2009-05-15 00:03:00",
            "post_id": "207030",
            "reply_to_id": "207025"
        },
        {
            "user_name": "Kobbmeister",
            "text": "Whut? \nÉg á leikinn ég bara týndi disknum",
            "date": "2009-05-15 20:24:00",
            "post_id": "207072",
            "reply_to_id": "207030"
        },
        {
            "user_name": "ÓmarSmith",
            "text": "Hvaða crack vantar þig þá eiginlega ?\nEf það er BARa CD-in sem er týndur þá vantar þig ekkert. CD key-ið er í bókinni sem er í hulstrinu.\nÉg hef aldrei notað neitt crack varðandi þennan leik.\nNema þú sért að tala um  NO CD crakcið... .það færðu hérna\nhttp://www.gamecopyworld.com\n \n   Getur fundið NO-DVD / No-CD crack    oft bara nýr EXE fæll. Lang best a nota það frekar en e-ð Deamon tools vesen,.",
            "date": "2009-05-15 20:59:00",
            "post_id": "207073",
            "reply_to_id": "207072"
        },
        {
            "user_name": "Kobbmeister",
            "text": "ok takk ég get nefnilega ekki spilað leikinn án disks, ég hélt að ég þurfti þá að cracka leikinn",
            "date": "2009-05-15 22:38:00",
            "post_id": "207077",
            "reply_to_id": "207073"
        },
        {
            "user_name": "ÓmarSmith",
            "text": "Bara minna aftur á ...\nSpread the word strákar.  skilst að þeir hjá Tölvutek séu að vinna í nýrri síðu og ætla að byrja að spila af krafti aftur núna. Við hljótum að ná amk 50 virkum BF2 spilurum.  Svo sem allt í lagi að hafa e-a útlendinga með, en bara já ... KOMA SVO !!",
            "date": "2009-05-25 14:51:00",
            "post_id": "207707",
            "reply_to_id": "207077"
        },
        {
            "user_name": "ÓmarSmith",
            "text": "Keep it alive !!\nAnnars er spurning um að við amk sem viljum spila förum að finna okkur bara breskan server til að spila saman á .\nhvernig líst ykkur á það ?",
            "date": "2009-05-29 15:23:00",
            "post_id": "207974",
            "reply_to_id": "207707"
        },
        {
            "user_name": "Halli25",
            "text": "Er nú eitthvað varið í BF2... ég keypti hann spilaði smá og gaf hann fannst hann svo leiðinlegur BF1944 FTW!",
            "date": "2009-05-29 16:27:00",
            "post_id": "207981",
            "reply_to_id": "207974"
        },
        {
            "user_name": "ÓmarSmith",
            "text": "njee.. BF2 er margfalt betri, mikið flottari, í alla staði og allt annað gameplay  bara.\nEina sem hefði mátt koma var WWII MOD fyrir Bf2, þá hefði hann verið unaður.\nHlakka bara til núna að komast í BF3 sem kemur í Júní á Xbox360",
            "date": "2009-05-29 16:37:00",
            "post_id": "207982",
            "reply_to_id": "207981"
        },
        {
            "user_name": "Orri",
            "text": "Leiðrétting, hann heitir Battlefield Bad Company 2, og hann kemur líka á PC og PS3.",
            "date": "2009-05-29 18:54:00",
            "post_id": "207988",
            "reply_to_id": "207982"
        },
        {
            "user_name": "ÓmarSmith",
            "text": "Leiðrétting..\nBad company er xbox360 og ps3\nen Bf1943 kemur á pc líka og er bara multiplay leikur með 4 borðum",
            "date": "2009-06-07 14:30:00",
            "post_id": "208675",
            "reply_to_id": "207988"
        },
        {
            "user_name": "Andriante",
            "text": "Battlefield leikirnir eru börn síns tíma. \nEf hitboxin væru ekki svona hrikalega ömurleg þá myndi maður spila BF leikina ennþá",
            "date": "2009-06-08 17:38:00",
            "post_id": "208793",
            "reply_to_id": "208675"
        },
        {
            "user_name": "Orri",
            "text": "Taktu eftir því að ég skrifa Bad Company \n2",
            "date": "2009-06-08 17:54:00",
            "post_id": "208795",
            "reply_to_id": "208793"
        },
        {
            "user_name": "ÓmarSmith",
            "text": "Já, Bad Company franchise-ið er bara fyrir consoles ..\nXBOX360 og PS3\nekkert PC þar á ferð \n ( Sem er reyndar svekk þar sem Bad Company er alveg frááábær leikur í alla staði )\n*EDIT\nÁkvað að breyta ekki textanum mínum..\nÉg gerði á mig þarna, sé á DICE síðunni að Bad Company 2 verður líka fyrir PC,  sem þíðir að þeir eru búnir að porta Frostbite engine yfir á PC líka \n  frábært mál.",
            "date": "2009-06-08 19:31:00",
            "post_id": "208805",
            "reply_to_id": "208795"
        },
        {
            "user_name": "Orri",
            "text": "Það var það sem ég var að reyna að segja \n \nReyndar breytti ég \"Taktu eftir því......\" póstinum mínum og bætti inn \" Bad Company 2 kemur líka á PC \" en það virðist ekki hafa skilað sér.",
            "date": "2009-06-08 19:38:00",
            "post_id": "208807",
            "reply_to_id": "208805"
        },
        {
            "user_name": "stefan251",
            "text": "eg er að spila bf 2",
            "date": "2009-09-02 11:30:00",
            "post_id": "217016",
            "reply_to_id": "208807"
        },
        {
            "user_name": "beggi90",
            "text": "Ég myndi klárlega kíkja ef það væri íslenskur server.",
            "date": "2009-09-02 11:58:00",
            "post_id": "217019",
            "reply_to_id": false
        }
    ],
    "date": "2009-09-02 11:58:00"
}