{
    "forum_title": "Sjónvörp, hljóðkerfi og snjalllausnir fyrir heimilið",
    "id": "44186",
    "title": "(Hjálp) Val á sjónvarpi",
    "url": "https://spjall.vaktin.is/viewtopic.php?f=47&t=44186",
    "posts": [
        {
            "user_name": "thorsteinn95",
            "text": "Ég hef verið í töluverðum vandræðum síðustu daga með að velja mér nýtt sjónvarp. Það verður mestmegnis notað fyrir PS3 tölvu og kvikmyndir og ég er að leita með budget upp að svona 140 þús.\nÉg er með nokkur tæki í huga en hef verið að velta fyrir mér hvað er best fyrir tölvuleiki svo sem LCD vs LED LCD vs Plasma.\nhttp://ht.is/index.php?sida=vara&vara=TXP42S30Y\n    (Plasma)\nhttp://ht.is/index.php?sida=vara&vara=32PFL4606H\n   (LCD)\nhttp://ht.is/index.php?sida=vara&vara=32PFL5606H\n   (LED LCD)\nVæri flott að fá álit á þessum tækjum og ábendingar fyrir val á sjónvarpi, takk fyrir",
            "date": "2011-12-22 16:04:00",
            "post_id": "406301",
            "reply_to_id": false
        },
        {
            "user_name": "thorsteinn95",
            "text": "Einnig að pæla í þessu frá Sony:\nhttp://www.netverslun.is/verslun/produc ... 3,621.aspx\nOg þess má geta að herbergið sem spilað er í er um 4x4 metrar og er opinn fyrir stærðum frá 32-42 tommur",
            "date": "2011-12-22 16:09:00",
            "post_id": "406304",
            "reply_to_id": "406301"
        },
        {
            "user_name": "gutti",
            "text": "Ég mundi mæla með Panasonic sjálfur ég er með 50 plasma  tæki frá  Panasonic",
            "date": "2011-12-22 16:27:00",
            "post_id": "406311",
            "reply_to_id": "406304"
        },
        {
            "user_name": "thorsteinn95",
            "text": "Takk fyrir, eru Plasma sjónvörp annars ekki betri fyrir PS3, útaf refresh-rateinu hjá þeim?",
            "date": "2011-12-22 20:14:00",
            "post_id": "406371",
            "reply_to_id": "406311"
        },
        {
            "user_name": "thorsteinn95",
            "text": "Fór áðan að skoða í Heimilistækjum, fannst Plasma ekki standa undir væntingum en LCD tækin með mun betri mynd. Maður þarf að vera með budget uppá svona 220þús til að fá Plasma með myndgæði á við LCD",
            "date": "2011-12-22 22:19:00",
            "post_id": "406395",
            "reply_to_id": "406371"
        },
        {
            "user_name": "blitz",
            "text": "Nei, LCD á langt í land til að ná Plasma í myndgæðum.\nSkoðaðu 42\" Panasonic Plasma (ST32) sem Sjónvarpsmiðstöðin er að selja á 195.000.",
            "date": "2011-12-22 22:31:00",
            "post_id": "406399",
            "reply_to_id": "406395"
        },
        {
            "user_name": "Minuz1",
            "text": "Ok, til höfundar greinarinnar...\nÞú ert að bera saman 42\" plasma tæki við 32\" LCD tæki.....er það eitthvað vafaatriði hversu sjónvarpið á að vera u.þ.b stórt?\nPeningarnir rokka um einhver 40% líka...veistu hvað þú vilt eyða í þetta?\nÞú færð aldrei gott plasma tæki sem er 32\" og keppir við LCD í verði.\n50\" og uppúr þá eru plasma miklu betri.\n42\" er örugglega einhver punktur þar sem sum LCD sjónvörp eru betri bang for buck heldur en plasma og öfugt, en það fer eftir þinni notkun.\nVæri fróðlegt ef þú getir sagt eitthvað annað sem gæti hjálpað okkur að hjálpa þér.\nEf ekki, þá myndi ég bara kaupa sjónvarpið sem þér lýst best á.\nErtu að kaupa Sjónvarp eftir \na) stærð?\nb) peningum?\nc) myndgæðum?",
            "date": "2011-12-23 01:44:00",
            "post_id": "406439",
            "reply_to_id": "406399"
        },
        {
            "user_name": "thorsteinn95",
            "text": "Já, ég var kannski frekar óskýr en verðhugmynd er um 100-140þús og stærð 37-42tommur. Er að leita að sem bestum myndgæðum fyrir PS3 og Blue-ray afspilun, takk.",
            "date": "2011-12-26 23:47:00",
            "post_id": "407633",
            "reply_to_id": "406439"
        },
        {
            "user_name": "blitz",
            "text": "http://sm.is/index.php?sida=vara&vara=TXP42S30Y\nhttp://www.hdtvtest.co.uk/news/panasoni ... 231578.htm\nMálið leyst",
            "date": "2011-12-27 07:46:00",
            "post_id": "407699",
            "reply_to_id": "407633"
        },
        {
            "user_name": "audiophile",
            "text": "Málið er aldrei svo einfalt. Þó að þetta virðist góður plasmi fyrir peninginn er gallinn við mörg plasmasjónvörp að þau henta illa í björtu umhverfi þar sem t.d. er stór stofugluggi og eins og hjá mér, viðbjóðsleg kvöldsól á sumrin. LCD kemur þá í flestum tilfellum betur út.",
            "date": "2011-12-27 12:36:00",
            "post_id": "407717",
            "reply_to_id": "407699"
        },
        {
            "user_name": "Haxdal",
            "text": "Þá bara fá sér myrkvunargardínu,  ekki gera einfaldan hlut flókinn",
            "date": "2011-12-27 13:18:00",
            "post_id": "407725",
            "reply_to_id": "407717"
        },
        {
            "user_name": "thorsteinn95",
            "text": "Ég fór í Sjónvarpsmiðstöðina og myndin á þessu sjónvarpi jafnast einfaldlega ekki á við LCD sjónvörpin, maður þarf að vera með budget uppá svona 250þús til að geta fengið sambærilegan plasma",
            "date": "2011-12-28 23:57:00",
            "post_id": "408117",
            "reply_to_id": "407725"
        },
        {
            "user_name": "pattzi",
            "text": "Panasonic lcd \nBúin að eiga eitt 32 tommu lcd sjónvarp síðan ég fermdist 2008 að koma 4 ár síðan og bara í fínu standi",
            "date": "2011-12-29 00:05:00",
            "post_id": "408119",
            "reply_to_id": "408117"
        }
    ],
    "date": "2011-12-22 16:04:00"
}