{
    "forum_title": "Hugbúnaðar- & Forritunarstofan",
    "id": "66870",
    "title": "Vantar mann í að gera vefsíðu",
    "url": "https://spjall.vaktin.is/viewtopic.php?f=7&t=66870",
    "posts": [
        {
            "user_name": "mundivalur",
            "text": "Sælir ég er að leita af einhverjum sem getur gert svona síðu fyrir mig en með nokkrum breytingum\nhttp://choosemypc.net/sleeving/\n þetta er svipað en snýr allt vitlaust fyrir mig og ss. bara til að velja liti ekkert annað\nSendið pm og ræðum launin",
            "date": "2015-09-09 17:48:00",
            "post_id": "606175",
            "reply_to_id": false
        },
        {
            "user_name": "kunglao",
            "text": "gangi þér vel.\nFrítt bömp",
            "date": "2015-09-10 11:37:00",
            "post_id": "606244",
            "reply_to_id": "606175"
        }
    ],
    "date": "2015-09-09 17:48:00"
}