{
    "forum_title": "Til sölu - Tölvuvörur",
    "id": "73485",
    "title": "Dell \"27 4K skjáir til sölu",
    "url": "https://spjall.vaktin.is/viewtopic.php?f=11&t=73485",
    "posts": [
        {
            "user_name": "emmi",
            "text": "2stk Dell Ultra HD (3840x2160) 27\" 4K LED skjáir til sölu, nokkurra vikna gamlir.\nhttps://vefverslun.advania.is/vefverslu ... LED-skjar/\n \nVerð: \n80þ\n 60þ\n** SELT **",
            "date": "2017-07-06 20:10:00",
            "post_id": "652644",
            "reply_to_id": false
        },
        {
            "user_name": "emmi",
            "text": "Upp.",
            "date": "2017-07-07 19:16:00",
            "post_id": "652739",
            "reply_to_id": "652644"
        },
        {
            "user_name": "emil40",
            "text": "Upp fyrir flottum skjá",
            "date": "2017-07-08 01:51:00",
            "post_id": "652760",
            "reply_to_id": "652739"
        },
        {
            "user_name": "emmi",
            "text": "Upp.",
            "date": "2017-07-13 07:44:00",
            "post_id": "653057",
            "reply_to_id": "652760"
        },
        {
            "user_name": "Rabcor",
            "text": "Ég væri til í hann en ég get bara borgað þér mest 50 fyrir hann. Sendi þér líka PM",
            "date": "2017-07-13 15:45:00",
            "post_id": "653092",
            "reply_to_id": "653057"
        },
        {
            "user_name": "Unicorn_24",
            "text": "Sæll\nÉg gæti tekið einn hjá þér ef þú værir til að seljann á 50.000kr?",
            "date": "2017-07-13 22:21:00",
            "post_id": "653122",
            "reply_to_id": "653092"
        },
        {
            "user_name": "emmi",
            "text": "Þakka boðið, ég var að lækka í 60 úr 80 þannig að ég fer ekki neðar.",
            "date": "2017-07-13 22:35:00",
            "post_id": "653124",
            "reply_to_id": "653122"
        }
    ],
    "date": "2017-07-06 20:10:00"
}