{
    "forum_title": "Húðflúr og götun",
    "user": "Swisha",
    "user_id": "44323",
    "date": "2008-10-22 11:16:45",
    "title": "Septum",
    "text": "Jæja elsku hugarar, á morgun er ég að fara að fá mér Septum! Ég er að deyja úr spenningi!\nEn ég vildi spurja ykkur pínu út í þetta, sérstaklega þá sem eru með þetta fallega gat.\n1. Er ekkert erfitt að snýta sér?\n2. Hve lengi verður bólgan?\n3. Hvernig byrjunarlokk voru þið með?\n4. Ég hef heyrt að það sé mjög auðvelt að fela lokkinn (s.s. inní nefinu), er eitthvað til í því?\nMeð von um góð svör.\n-Nína\nBætt við 22. október 2008 -  12:24\nog eitt annað:\nHvort mæliði með skeifu eða pinna sem byrjunarlokk?\nÉg þarf að geta falið þetta útaf vinnunni..",
    "url": "https://www.hugi.is/hudflur/korkar/621131/septum/",
    "url_id": "621131",
    "id": "6230742",
    "replies": [
        {
            "user": "Fenrir",
            "user_id": "34852",
            "date": "2008-10-22 11:25:03",
            "id": "6230751",
            "reply_to_id": "6230742",
            "text": "Það er jafn erfitt að snýta sér með lokk og án hans.\nBólgan er ekki svo rosaleg. Ég fékk mér septum sama dag og Cannibal Corpse voru að spila hérna, fór á tónleikana um kvöldið og slammaði eins og fáviti. Ekki meira vesen en það :)\nÉg var bara með “opinn” hring með 2 kúlum í staðinn fyrir eina til að byrja með.\nÞað er ekkert mál að fela lokkinn. Ég er oftast með beinan pinna, svipaðan og er notað í tungu nema bara styttri, í gatinu því ég þarf að fela það vegna vinnunnar.\nGangi þér bara vel með þetta :)"
        },
        {
            "user": "Swisha",
            "user_id": "44323",
            "date": "2008-10-22 11:28:37",
            "id": "6230762",
            "reply_to_id": "6230751",
            "text": "takk fyrir svörin :)\nEn það er líka annað, ég þarf að fela lokkinn útaf vinnunni, mynduru þá frekar mæla með pinna sem byrjunarlokk?"
        },
        {
            "user": "Fenrir",
            "user_id": "34852",
            "date": "2008-10-22 12:06:47",
            "id": "6230824",
            "reply_to_id": "6230762",
            "text": "Já."
        },
        {
            "user": "neonballroom",
            "user_id": "61087",
            "date": "2008-10-22 13:33:53",
            "id": "6231011",
            "reply_to_id": "6230742",
            "text": "1. Ég tók minn lokk úr þegar ég var sérstaklega kvefuð, þá var vont að snýta sér, en annars var það ekkert mál.\n2. Bólgan hjá mér fór eiginlega aldrei. Ég var bólgin og hálfaum meira og minna allan tímann sem ég var með gatið, afþví ég var alltaf að reka nebbann í hitt og þetta.\n3. Ég fékk mitt hjá Sessu og hún lét mig fá svona næstum því heilan hring, ætli það sé ekki skeifan sem þú talar um.\n4. Það var ekkert mál að snúa hringnum við til að fela gatið, þó ég væri með skeifuna. Ég er samt víst með eitthvað frekar breitt miðnes svo Sessa þurfti aðeins að breikka lokkinn fyrir mig, bara teygja hann í sundum með töngum. Þá varð ekkert mál að fela lokkinn.\nAnnars, til hammó með að vera að fá septum. Ég sakna míns."
        },
        {
            "user": "Swisha",
            "user_id": "44323",
            "date": "2008-10-22 14:08:09",
            "id": "6231105",
            "reply_to_id": "6231011",
            "text": "takk kærlega fyrir svörin :)\nÉg er að deyja úr spenningi!"
        },
        {
            "user": "Erlakisa",
            "user_id": "61905",
            "date": "2008-10-22 16:08:36",
            "id": "6231571",
            "reply_to_id": "6230742",
            "text": "1. Nei, ég varð kvefuð rétt eftir að ég fékk gatið og fannst ekkert erfiðara að snýta mér.\n2. Ég var aum í nokkra daga en það var ekkert svakalegt.\n3. Svona “skeifu” með kúlum á báðum endum.\n4. Já, það er lítið mál. En ef þú færð svona skeifu lokk þá held ég að það sé gott að reyna að vera ekki að hreyfa hann of mikið allavega fyrstu dagana.\nMá ég spurja, hvernig vinnu ertu í?"
        },
        {
            "user": "Swisha",
            "user_id": "44323",
            "date": "2008-10-22 17:46:45",
            "id": "6231886",
            "reply_to_id": "6231571",
            "text": "takk kærlega fyrir svörin :)\nég vinn sem kassadama í BT og það er ekkert sjálfagt að ég sé með götin í vinnunni, þarf alltaf að taka snakebitið úr, sem er pain -.-\""
        },
        {
            "user": "Erlakisa",
            "user_id": "61905",
            "date": "2008-10-22 19:37:11",
            "id": "6232213",
            "reply_to_id": "6231886",
            "text": "What, geturu tekið lokkana úr í nokkra klukkutíma og sett þá aftur í? Ég lennti einu sinni í að lokkur datt úr hjá mér (í vörini) og það var gróið fyrir það eftir 2 klukkutíma :/\nEn já, ég myndi ekki meika að vinna þar sem ég get ekki verið með lokka O.o Er með 5 andlitsgöt :P"
        },
        {
            "user": "Swisha",
            "user_id": "44323",
            "date": "2008-10-22 20:54:34",
            "id": "6232428",
            "reply_to_id": "6232213",
            "text": "haha, trikkið mitt er að ég geymi lokk í kinninni og síðan þegar engin er að horfa þá ýti ég lokknum í gegnum götin svo að þau grói ekki :)"
        },
        {
            "user": "Erlakisa",
            "user_id": "61905",
            "date": "2008-10-22 22:31:29",
            "id": "6232696",
            "reply_to_id": "6232428",
            "text": "Haha, nice :P Ég myndi samt svo ekki nenna því XD"
        },
        {
            "user": "Swisha",
            "user_id": "44323",
            "date": "2008-10-23 16:44:53",
            "id": "6234138",
            "reply_to_id": "6232428",
            "text": "ertu þá ekki alltaf með bullandi fossandi sýkingu?"
        },
        {
            "user": "Swisha",
            "user_id": "44323",
            "date": "2008-10-23 17:00:42",
            "id": "6234191",
            "reply_to_id": "6234138",
            "text": "nefnilega ekki :D"
        },
        {
            "user": "unaarna",
            "user_id": "62557",
            "date": "2008-10-22 17:28:43",
            "id": "6231814",
            "reply_to_id": "6230742",
            "text": "afhverju þarftu að fela:) ?\nvið hvað vinnuru eila :D ?"
        },
        {
            "user": "Swisha",
            "user_id": "44323",
            "date": "2008-10-22 17:47:14",
            "id": "6231887",
            "reply_to_id": "6231814",
            "text": "er kassadama í BT, og það er ekkert sjálfagt að ég sé með götin í vinnunni :Þ"
        },
        {
            "user": "unaarna",
            "user_id": "62557",
            "date": "2008-10-22 17:48:24",
            "id": "6231892",
            "reply_to_id": "6231887",
            "text": "er það bannað eða eithtvað svoleiðis :)?\nhef aldrei pælt i þvi ;p"
        },
        {
            "user": "Swisha",
            "user_id": "44323",
            "date": "2008-10-22 17:50:01",
            "id": "6231899",
            "reply_to_id": "6231892",
            "text": "já, það er sagt í reglunum að maður á að vera snyrtilegur til fara og ekki með sýnilega lokka í andlitinu, samt finnast samstarfsmönnunum mínum þetta algjört bull.\nEn maður verður að fórna ýmsu til að halda vinnunni sinni :Þ"
        },
        {
            "user": "unaarna",
            "user_id": "62557",
            "date": "2008-10-22 17:51:14",
            "id": "6231905",
            "reply_to_id": "6231899",
            "text": "haha eg mundi ekki nenna að hlíða eitthverjum reglum 8)\nþetta eru bara loftgöt :D !\nhver veit kannski áttu erfitt með að anda ?\nen ertu komin með þetta septum gat :D ?"
        },
        {
            "user": "Swisha",
            "user_id": "44323",
            "date": "2008-10-22 18:31:12",
            "id": "6232032",
            "reply_to_id": "6231905",
            "text": "haha!\nnei, ég fæ mér það á morgun eftir vinnu, get ekki beðið! :D"
        },
        {
            "user": "unaarna",
            "user_id": "62557",
            "date": "2008-10-23 19:14:04",
            "id": "6234754",
            "reply_to_id": "6232032",
            "text": "semsagt i dag :D\ntil hamingju með nýja gatið 8) ;p"
        },
        {
            "user": "Swisha",
            "user_id": "44323",
            "date": "2008-10-23 22:25:31",
            "id": "6235489",
            "reply_to_id": "6234754",
            "text": "takk takk :D\nÉg er súber ánægð :D"
        },
        {
            "user": "unaarna",
            "user_id": "62557",
            "date": "2008-10-25 09:35:35",
            "id": "6239101",
            "reply_to_id": "6235489",
            "text": "ooosom 8]"
        },
        {
            "user": "neonballroom",
            "user_id": "61087",
            "date": "2008-10-25 21:37:17",
            "id": "6240567",
            "reply_to_id": "6231899",
            "text": "Spes að þetta sé svona í BT, í Elko eru nánast allar kassadömurnar með 20 göt í andlitinu :P"
        },
        {
            "user": "Swisha",
            "user_id": "44323",
            "date": "2008-10-26 01:01:53",
            "id": "6241025",
            "reply_to_id": "6240567",
            "text": "já hef heyrt af því :Þ"
        },
        {
            "user": "Eliiin",
            "user_id": "69186",
            "date": "2008-10-22 21:54:03",
            "id": "6232597",
            "reply_to_id": "6230742",
            "text": "oo mig langar svo i septum en er ekki aaaalveg viss hvort að það fari mer :)\nBætt við 22. október 2008 -  21:59\nsettu bara beinan pinna ,, eg setti allavega bara beinan pinna í egil þegar að eg gerði hans það var mjög fint :)"
        }
    ]
}